notebook_to_blog/__init__.py
notebook_to_blog/cells.py
notebook_to_blog/cli.py
notebook_to_blog/constants.py
notebook_to_blog/gist.py
notebook_to_blog/notebook.py
notebook_to_blog-0.0.1.dist-info/LICENSE
notebook_to_blog-0.0.1.dist-info/METADATA
notebook_to_blog-0.0.1.dist-info/WHEEL
notebook_to_blog-0.0.1.dist-info/entry_points.txt
notebook_to_blog-0.0.1.dist-info/top_level.txt
notebook_to_blog-0.0.1.dist-info/RECORD
