Metadata-Version: 2.1
Name: notebook-to-blog
Version: 0.0.1
Summary: Convert a Jupyter notebook to blog ready format
Home-page: UNKNOWN
Author: Chris Rinaldi
Author-email: cgrinaldi@gmail.com
License: MIT
Platform: UNKNOWN
Requires-Dist: Click
Requires-Dist: PyGithub
Requires-Dist: python-dotenv
